filestorage/VERSION
filestorage/__init__.py
filestorage/__init__.pyi
filestorage/config_utils.py
filestorage/config_utils.pyi
filestorage/exceptions.py
filestorage/exceptions.pyi
filestorage/file_item.py
filestorage/file_item.pyi
filestorage/filter_base.py
filestorage/filter_base.pyi
filestorage/handler_base.py
filestorage/handler_base.pyi
filestorage/py.typed
filestorage/pyramid_config.py
filestorage/pyramid_config.pyi
filestorage/storage_container.py
filestorage/storage_container.pyi
filestorage/utils.py
filestorage/utils.pyi
filestorage/filters/__init__.py
filestorage/filters/__init__.pyi
filestorage/filters/_template.py
filestorage/filters/_template.pyi
filestorage/filters/py.typed
filestorage/filters/randomize_filename.py
filestorage/filters/randomize_filename.pyi
filestorage/filters/valid_extensions.py
filestorage/filters/valid_extensions.pyi
filestorage/handlers/__init__.py
filestorage/handlers/__init__.pyi
filestorage/handlers/_template.py
filestorage/handlers/_template.pyi
filestorage/handlers/dummy.py
filestorage/handlers/dummy.pyi
filestorage/handlers/file.py
filestorage/handlers/file.pyi
filestorage/handlers/py.typed
filestorage/handlers/s3.py
filestorage/handlers/s3.pyi
filestorage-0.0.6.dist-info/LICENSE
filestorage-0.0.6.dist-info/METADATA
filestorage-0.0.6.dist-info/WHEEL
filestorage-0.0.6.dist-info/top_level.txt
filestorage-0.0.6.dist-info/RECORD
