Metadata-Version: 2.1
Name: filestorage
Version: 0.0.6
Summary: Save uploaded files in configurable stores
Home-page: https://github.com/ianepperson/filestorage
Author: Ian Epperson
Author-email: ian@epperson.com
License: UNKNOWN
Platform: any
Classifier: Programming Language :: Python :: 3
Classifier: License :: OSI Approved :: MIT License
Classifier: Operating System :: OS Independent
Requires-Python: >=3.6
Provides-Extra: aio_file
Provides-Extra: s3
Provides-Extra: test
